portopt/__init__.py
portopt/backtesting.py
portopt/data.py
portopt/factor.py
portopt/plotting.py
portopt/semivariance.py
portopt/utils.py
PortfolioOptimization-0.0.11.dist-info/LICENSE.md
PortfolioOptimization-0.0.11.dist-info/METADATA
PortfolioOptimization-0.0.11.dist-info/WHEEL
PortfolioOptimization-0.0.11.dist-info/top_level.txt
PortfolioOptimization-0.0.11.dist-info/RECORD
