Metadata-Version: 2.1
Name: PortfolioOptimization
Version: 0.0.11
Summary: A package for portfolio optimization.
Home-page: https://github.com/nathanramoscfa/PortfolioOptimization.git
Author: Nathan Ramos, CFA®
Author-email: nathan.ramos.github@gmail.com
Classifier: Development Status :: 3 - Alpha
Classifier: Intended Audience :: Financial and Insurance Industry
Classifier: Intended Audience :: Developers
Classifier: License :: OSI Approved :: MIT License
Classifier: Programming Language :: Python :: 3
Classifier: Programming Language :: Python :: 3.8
Classifier: Programming Language :: Python :: 3.9
Classifier: Programming Language :: Python :: 3.10
Classifier: Programming Language :: Python :: 3.11
Requires-Python: >=3.8
License-File: LICENSE.md
Requires-Dist: beautifulsoup4 >=4.12.2
Requires-Dist: bt >=0.2.9
Requires-Dist: cvxpy >=1.3.2
Requires-Dist: ffn >=0.3.7
Requires-Dist: matplotlib >=3.7.1
Requires-Dist: numpy >=1.23.5
Requires-Dist: pandas >=2.1.0
Requires-Dist: pyportfolioopt >=1.5.5
Requires-Dist: requests >=2.31.0
Requires-Dist: scipy >=1.11.2
Requires-Dist: seaborn >=0.12.2
Requires-Dist: setuptools >=68.0.0
Requires-Dist: tqdm >=4.65.0
Requires-Dist: yahooquery ==2.3.6
